odoo/addons/repair_type_security/README.rst
odoo/addons/repair_type_security/__init__.py
odoo/addons/repair_type_security/__manifest__.py
odoo/addons/repair_type_security/hook.py
odoo/addons/repair_type_security/i18n/repair_type_security.pot
odoo/addons/repair_type_security/readme/CONTRIBUTORS.rst
odoo/addons/repair_type_security/readme/DESCRIPTION.rst
odoo/addons/repair_type_security/security/ir.model.access.csv
odoo/addons/repair_type_security/static/description/icon.png
odoo/addons/repair_type_security/static/description/index.html
odoo_addon_repair_type_security-15.0.1.0.0.2.dist-info/METADATA
odoo_addon_repair_type_security-15.0.1.0.0.2.dist-info/WHEEL
odoo_addon_repair_type_security-15.0.1.0.0.2.dist-info/top_level.txt
odoo_addon_repair_type_security-15.0.1.0.0.2.dist-info/RECORD
