Metadata-Version: 2.1
Name: odoo-addon-repair-type-security
Version: 15.0.1.0.0.2
Summary: Glue module Repair Type and Repair Security
Home-page: https://github.com/OCA/repair
Author: ForgeFlow S.L., Odoo Community Association (OCA)
Author-email: support@odoo-community.org
License: AGPL-3
Platform: UNKNOWN
Classifier: Programming Language :: Python
Classifier: Framework :: Odoo
Classifier: Framework :: Odoo :: 15.0
Classifier: License :: OSI Approved :: GNU Affero General Public License v3
Classifier: Development Status :: 3 - Alpha
Requires-Python: >=3.8
Requires-Dist: odoo-addon-repair-security <15.1dev,>=15.0dev
Requires-Dist: odoo-addon-repair-type <15.1dev,>=15.0dev
Requires-Dist: odoo <15.1dev,>=15.0a
